<?xml version="1.0" encoding="ISO-8859-1"?>

<suite name="AllTests Suite">
    <test name="First">
        <groups>
            <run>
                <include name = "first"/>
            </run>
        </groups>
        <classes>
            <class name="grouping.Groups"/>

        </classes>
    </test>
    <test name="Second">
        <groups>
            <run>
                <include name = "second"/>
            </run>
        </groups>
        <classes>
            <class name="grouping.Groups"/>

        </classes>
    </test>

</suite>




